gemspeak/__init__.py
gemspeak/client.py
gemspeak/data.py
gemspeak/files.py
gemspeak/response.py
gemspeak/settings.py
gemspeak-1.1.4.dist-info/METADATA
gemspeak-1.1.4.dist-info/WHEEL
gemspeak-1.1.4.dist-info/licenses/LICENSE
gemspeak-1.1.4.dist-info/RECORD
