Metadata-Version: 2.4
Name: gemspeak
Version: 1.1.4
Summary: A Python library to manage multiple Google Gemini API keys and interact with the API easily.
Project-URL: Homepage, https://github.com/att131/gemspeak
Project-URL: Bug Tracker, https://github.com/att131/gemspeak/issues
Project-URL: Source, https://github.com/att131/gemspeak
Project-URL: Documentation, https://github.com/att131/gemspeak#readme
Author-email: Atticus Alarcon <atticusaalarcon@gmail.com>
License: Copyright 2025 Atticus Alarcon
License-File: LICENSE
Keywords: ai,api,gemini,gemini-api,gemspeak,google
Classifier: License :: OSI Approved :: MIT License
Classifier: Operating System :: OS Independent
Classifier: Programming Language :: Python :: 3
Requires-Python: >=3.8
Requires-Dist: appdirs>=1.4.4
Requires-Dist: google-api-core>=2.24.2
Requires-Dist: google-genai>=1.19.0
Requires-Dist: requests>=2.23.3
